bit_field/__init__.py
bit_field/__main__.py
bit_field/cli.py
bit_field/jsonml_stringify.py
bit_field/render.py
bit_field/tspan.py
bitfield_extended-1.2.0.dist-info/licenses/LICENSE
bitfield_extended-1.2.0.dist-info/licenses/LICENSE-ORIGINAL
bitfield_extended-1.2.0.dist-info/METADATA
bitfield_extended-1.2.0.dist-info/WHEEL
bitfield_extended-1.2.0.dist-info/entry_points.txt
bitfield_extended-1.2.0.dist-info/top_level.txt
bitfield_extended-1.2.0.dist-info/RECORD
