Metadata-Version: 2.4
Name: bitfield-extended
Version: 1.2.0
Summary: A bitfield diagram renderer
Home-page: https://github.com/Taron686/bitfield
Author: Andreas Wambold
License: MIT
Keywords: bitfield,bytefield,diagram,renderer,svg
Classifier: Programming Language :: Python :: 3
Classifier: License :: OSI Approved :: MIT License
Classifier: Operating System :: OS Independent
License-File: LICENSE
License-File: LICENSE-ORIGINAL
Provides-Extra: json5
Requires-Dist: json5>=0.9.6; extra == "json5"
Dynamic: license-file
